mydev-0.0.2.dist-info/METADATA
mydev-0.0.2.dist-info/WHEEL
mydev-0.0.2.dist-info/entry_points.txt
mydev/__init__.py
mydev/agent/__init__.py
mydev/agent/main.py
mydev/agent/models.py
mydev/assets/install.sh
mydev/cli/__init__.py
mydev/cli/agent.py
mydev/cli/db.py
mydev/cli/infra.py
mydev/cli/main.py
mydev/cli/pm.py
mydev/config.py
mydev/console.py
mydev/db.py
mydev/infra/__init__.py
mydev/infra/shell.py
mydev/models/__init__.py
mydev/pm/__init__.py
mydev/pm/manager.py
mydev/pm/models.py
mydev/utils/__init__.py
mydev/utils/constants.py
mydev/utils/monitoring.py
mydev/utils/secrets.py
mydev/utils/ssh.py
mydev-0.0.2.dist-info/RECORD
